bitcoind_mock/__init__.py
bitcoind_mock/auth_proxy.py
bitcoind_mock/bitcoind.py
bitcoind_mock/conf.py
bitcoind_mock/rpc_errors.py
bitcoind_mock/sample_conf.py
bitcoind_mock/transaction.py
bitcoind_mock/utils.py
bitcoind_mock/zmq_publisher.py
test/__init__.py
test/unit/__init__.py
test/unit/conftest.py
test/unit/test_bitcoind_mock.py
bitcoind_mock-0.0.5.dist-info/LICENSE
bitcoind_mock-0.0.5.dist-info/METADATA
bitcoind_mock-0.0.5.dist-info/WHEEL
bitcoind_mock-0.0.5.dist-info/top_level.txt
bitcoind_mock-0.0.5.dist-info/RECORD
