Metadata-Version: 2.1
Name: bitcoind-mock
Version: 0.0.5
Summary: A tiny and non-exhaustive mock for bitcoind
Home-page: https://github.com/sr-gi/bitcoind_mock
Author: Sergi Delgado Segura
Author-email: sergi.delgado.s@gmail.com
License: UNKNOWN
Platform: UNKNOWN
Classifier: Programming Language :: Python :: 3
Classifier: License :: OSI Approved :: MIT License
Classifier: Operating System :: OS Independent
Requires-Python: >=3.6
Requires-Dist: zmq
Requires-Dist: networkx
Requires-Dist: flask
Requires-Dist: requests
Requires-Dist: riemann-tx (==2.1.0)
